README.md
setup.py
django_pmedien_export/__init__.py
django_pmedien_export/pmedien_export.py
django_pmedien_export.egg-info/PKG-INFO
django_pmedien_export.egg-info/SOURCES.txt
django_pmedien_export.egg-info/dependency_links.txt
django_pmedien_export.egg-info/requires.txt
django_pmedien_export.egg-info/top_level.txt