Metadata-Version: 2.1
Name: django-pmedien-export
Version: 0.21
Summary: General export for a complete model with languages
Home-page: http://www.pmedien.com
Author: pmedien GmbH
Author-email: nomail@pmedien.com
License: MIT
Platform: UNKNOWN
Requires-Python: >=2.7
